.editorconfig
.travis.yml
AUTHORS.rst
CHANGELOG.rst
CONTRIBUTING.rst
LICENSE
MANIFEST.in
README.rst
flit.ini
pytest.ini
requirements.txt
setup.cfg
setup.py
tox.ini
docs/Makefile
docs/authors.rst
docs/changelog.rst
docs/conf.py
docs/contributing.rst
docs/index.rst
docs/make.bat
docs/readme.rst
docs/requirements.txt
docs/drafts/livecircuits-design.rst
requirements/base.txt
requirements/docs.txt
requirements/tests.txt
sf/__init__.py
sf/arp/__init__.py
sf/fm/__init__.py
sf/fm/presets.py
sf/fm/synth.py
sf/polyphonist/__init__.py
sf/polyphonist/module.py
sf/polyphonist/pattern.py
sf/synth/__init__.py
sf/synth/sunsynth.py
sf/tools/__init__.py
sf/tools/midisynth.py
solar_flares.egg-info/PKG-INFO
solar_flares.egg-info/SOURCES.txt
solar_flares.egg-info/dependency_links.txt
solar_flares.egg-info/not-zip-safe
solar_flares.egg-info/requires.txt
solar_flares.egg-info/top_level.txt
tests/__init__.py
tests/test_nothing.py